README.rst
setup.cfg
setup.py
./utils.py
bin/trytond_sentry
trytond_sentry.egg-info/PKG-INFO
trytond_sentry.egg-info/SOURCES.txt
trytond_sentry.egg-info/dependency_links.txt
trytond_sentry.egg-info/not-zip-safe
trytond_sentry.egg-info/requires.txt
trytond_sentry.egg-info/top_level.txt