Metadata-Version: 1.1
Name: trytond-sentry
Version: 5.0.0.1
Summary: Sentry Client for Tryton
Home-page: https://github.com/fulfilio/trytond-sentry
Author: Fulfil.IO Inc., Openlabs Technologies & Consulting (P) Limited
Author-email: info@fulfil.io
License: BSD
Platform: UNKNOWN
Classifier: Development Status :: 5 - Production/Stable
Classifier: Environment :: Plugins
Classifier: Intended Audience :: Developers
Classifier: License :: OSI Approved :: GNU General Public License (GPL)
Classifier: Natural Language :: English
Classifier: Operating System :: OS Independent
Classifier: Programming Language :: Python
Classifier: Topic :: Office/Business
